[
  {
    "id": "easy_meeting-17",
    "title": "Workshop",
    "eventType": "meeting",
    "start": "2018-02-06T13:00:00+01:00",
    "end": "2018-02-06T14:30:00+01:00",
    "allDay": false,
    "editable": true,
    "url": "/easy_meetings/17",
    "location": null
  },
  {
    "id": "easy_meeting-18",
    "title": "Lunch with CEO",
    "eventType": "meeting",
    "start": "2018-02-05T12:00:00+01:00",
    "end": "2018-02-05T13:00:00+01:00",
    "allDay": false,
    "editable": true,
    "url": "/easy_meetings/18",
    "location": null
  },
  {
    "id": "easy_meeting-19",
    "title": "Flight to Stockholm",
    "eventType": "meeting",
    "start": "2018-02-07T14:30:00+01:00",
    "end": "2018-02-07T18:00:00+01:00",
    "allDay": false,
    "editable": true,
    "url": "/easy_meetings/19",
    "location": null
  },
  {
    "id": "easy_meeting-20",
    "title": "Return flight from Stockholm",
    "eventType": "meeting",
    "start": "2018-02-09T10:00:00+01:00",
    "end": "2018-02-09T14:30:00+01:00",
    "allDay": false,
    "editable": true,
    "url": "/easy_meetings/20",
    "location": null
  },
  {
    "id": "easy_meeting-21",
    "title": "Doctor appoointment",
    "eventType": "meeting",
    "start": "2018-02-08T10:00:00+01:00",
    "end": "2018-02-08T11:30:00+01:00",
    "allDay": false,
    "editable": true,
    "url": "/easy_meetings/21",
    "location": null
  },
  {
    "id": "availability-easy-attendance-calendar-event-105",
    "title": "Dovolená",
    "eventType": "easy_attendance",
    "start": "2018-02-09T09:00:00+01:00",
    "end": "2018-02-09T17:00:00+01:00",
    "allDay": true,
    "editable": false
  },
  {
    "id": "availability-easy-entity-activity-calendar-event-49",
    "title": "Ferilia: Call",
    "eventType": "easy_entity_activity",
    "start": "2018-02-05T13:00:00+01:00",
    "end": "2018-02-05T14:00:00+01:00",
    "allDay": false,
    "editable": false
  }
]
